game280/__init__.py
game280/_base.py
game280/_physics_global.py
game280/_utils.py
game280/helpers.py
game280/objects.py
game280/physics.py
game280/py.typed
game280/renderers.py
game280/resources.py
game280/backends/__init__.py
game280/backends/_base.py
game280/backends/pygame.py
game280/backends/pyodide.py
game280/examples/__init__.py
game280/examples/physics.py
game280/examples/platformer.py
game280-0.1.1.dist-info/METADATA
game280-0.1.1.dist-info/WHEEL
game280-0.1.1.dist-info/licenses/LICENSE
game280-0.1.1.dist-info/RECORD
